gradescope_utils/__init__.py
gradescope_utils/autograder_utils/__init__.py
gradescope_utils/autograder_utils/decorators.py
gradescope_utils/autograder_utils/files.py
gradescope_utils/autograder_utils/json_test_runner.py
gradescope_utils-0.5.0.dist-info/LICENSE
gradescope_utils-0.5.0.dist-info/METADATA
gradescope_utils-0.5.0.dist-info/WHEEL
gradescope_utils-0.5.0.dist-info/top_level.txt
gradescope_utils-0.5.0.dist-info/RECORD
