Metadata-Version: 2.1
Name: gradescope-utils
Version: 0.5.0
Summary: Utilities for building Gradescope autograders
Home-page: https://github.com/gradescope/gradescope-utils
Author: Ibrahim Awwal
Author-email: ibrahim@gradescope.com
License: MIT
Keywords: gradescope http service
Classifier: Development Status :: 3 - Alpha
Classifier: Intended Audience :: Developers
Classifier: Topic :: Software Development :: Build Tools
Classifier: License :: OSI Approved :: MIT License
Classifier: Programming Language :: Python :: 2
Classifier: Programming Language :: Python :: 2.6
Classifier: Programming Language :: Python :: 2.7
Classifier: Programming Language :: Python :: 3
Classifier: Programming Language :: Python :: 3.3
Classifier: Programming Language :: Python :: 3.4
Classifier: Programming Language :: Python :: 3.5
Provides-Extra: dev
Provides-Extra: test
License-File: LICENSE
